iptvtools/__init__.py
iptvtools/cli.py
iptvtools/config.py
iptvtools/exceptions.py
iptvtools/models.py
iptvtools/parsers.py
iptvtools/py.typed
iptvtools/settings.py
iptvtools/utils.py
iptvtools/constants/__init__.py
iptvtools/constants/defaults.py
iptvtools/constants/helps.py
iptvtools/constants/patterns.py
iptvtools/constants/tags.py
iptvtools-0.3.1.dist-info/LICENSE
iptvtools-0.3.1.dist-info/METADATA
iptvtools-0.3.1.dist-info/WHEEL
iptvtools-0.3.1.dist-info/entry_points.txt
iptvtools-0.3.1.dist-info/top_level.txt
iptvtools-0.3.1.dist-info/RECORD
