Metadata-Version: 2.2
Name: iptvtools
Version: 0.3.1
Summary: A set of scripts that help to better IPTV experience.
Author-email: huxuan <i@huxuan.org>
License: MIT
Project-URL: documentation, https://huxuan.github.io/iptvtools
Project-URL: issue, https://github.com/huxuan/iptvtools/issues
Project-URL: repository, https://github.com/huxuan/iptvtools
Keywords: iptvtools,iptvtools-cli,m3u filter,serious-scaffold
Classifier: Development Status :: 4 - Beta
Classifier: License :: OSI Approved :: MIT License
Classifier: Operating System :: MacOS :: MacOS X
Classifier: Operating System :: POSIX :: Linux
Classifier: Programming Language :: Python :: 3 :: Only
Classifier: Programming Language :: Python :: 3.10
Classifier: Programming Language :: Python :: 3.11
Classifier: Programming Language :: Python :: 3.12
Classifier: Programming Language :: Python :: 3.13
Requires-Python: >=3.10
License-File: LICENSE
Requires-Dist: click>=8.1.8
Requires-Dist: pydantic-settings>=2.7.1
Requires-Dist: requests>=2.32.3
Requires-Dist: tqdm>=4.67.1
